bggcli/__init__.py
bggcli/main.py
bggcli/version.py
bggcli/commands/__init__.py
bggcli/commands/collection_delete.py
bggcli/commands/collection_export.py
bggcli/commands/collection_import.py
bggcli/ui/__init__.py
bggcli/ui/collectionpage.py
bggcli/ui/gamepage.py
bggcli/ui/loginpage.py
bggcli/util/__init__.py
bggcli/util/csvreader.py
bggcli/util/logger.py
bggcli/util/webdriver.py
bggcli/util/xmltocsv.py
bggcli2018-1.0a1.dist-info/DESCRIPTION.rst
bggcli2018-1.0a1.dist-info/METADATA
bggcli2018-1.0a1.dist-info/RECORD
bggcli2018-1.0a1.dist-info/WHEEL
bggcli2018-1.0a1.dist-info/entry_points.txt
bggcli2018-1.0a1.dist-info/metadata.json
bggcli2018-1.0a1.dist-info/top_level.txt
