Metadata-Version: 2.0
Name: bggcli2018
Version: 1.0a1
Summary: Command Line Interface for BoardGameGeek.com
Home-page: http://github.org/HiGregSmith/bggcli
Author: Greg Smith <ecomputerd@yahoo.com>, Sylvain Francois <syllant@gmail.com>
Author-email: ecomputerd@yahoo.com
License: MIT
Requires-Dist: selenium
Requires-Dist: docopt
